ezjson.py
setup.py
ezjson.egg-info/PKG-INFO
ezjson.egg-info/SOURCES.txt
ezjson.egg-info/dependency_links.txt
ezjson.egg-info/top_level.txt