Metadata-Version: 1.1
Name: ezjson
Version: 1.0
Summary: Ezjson (means easy json) is a simple python module to encode and decode json.
Home-page: http://github.com/sacanix/ezjson
Author: Tony Kamillo (Sacanix)
Author-email: tonysacanix@gmail.com
License: BSD
Platform: any
Classifier: Environment :: Web Environment
Classifier: Intended Audience :: Developers
Classifier: License :: OSI Approved :: BSD License
Classifier: Operating System :: OS Independent
Classifier: Programming Language :: Python
Classifier: Topic :: Internet :: WWW/HTTP :: Dynamic Content
